setup.cfg
setup.py
openidprovider_middleware/__init__.py
openidprovider_middleware/openidprovider.py
openidprovider_middleware.egg-info/PKG-INFO
openidprovider_middleware.egg-info/SOURCES.txt
openidprovider_middleware.egg-info/dependency_links.txt
openidprovider_middleware.egg-info/requires.txt
openidprovider_middleware.egg-info/top_level.txt