Metadata-Version: 1.0
Name: openidprovider-middleware
Version: 0.1
Summary: OpenID provider middleware for WSGI applications
Home-page: http://hg.sandbox.lt/openidprovider-middleware
Author: Dalius Dobravolskas
Author-email: dalius@sandbox.lt
License: MIT
Platform: UNKNOWN
